README.md
setup.cfg
setup.py
qgis2to3/__init__.py
qgis2to3.egg-info/PKG-INFO
qgis2to3.egg-info/SOURCES.txt
qgis2to3.egg-info/dependency_links.txt
qgis2to3.egg-info/top_level.txt
qgis2to3/api2finder/__init__.py
qgis2to3/api2finder/matchesdict.py
qgis2to3/api2finder/merge_duplicates.py
qgis2to3/api2finder/qgis2apifinder
qgis2to3/codeporting/__init__.py
qgis2to3/codeporting/qgis2to3
qgis2to3/codeporting/qgis_fixes/__init__.py
qgis2to3/codeporting/qgis_fixes/fix_absolute_import.py
qgis2to3/codeporting/qgis_fixes/fix_apply.py
qgis2to3/codeporting/qgis_fixes/fix_basestring.py
qgis2to3/codeporting/qgis_fixes/fix_cmp.py
qgis2to3/codeporting/qgis_fixes/fix_dict.py
qgis2to3/codeporting/qgis_fixes/fix_except.py
qgis2to3/codeporting/qgis_fixes/fix_exec.py
qgis2to3/codeporting/qgis_fixes/fix_execfile.py
qgis2to3/codeporting/qgis_fixes/fix_exitfunc.py
qgis2to3/codeporting/qgis_fixes/fix_filter.py
qgis2to3/codeporting/qgis_fixes/fix_funcattrs.py
qgis2to3/codeporting/qgis_fixes/fix_future_builtins.py
qgis2to3/codeporting/qgis_fixes/fix_future_standard_library.py
qgis2to3/codeporting/qgis_fixes/fix_future_standard_library_urllib.py
qgis2to3/codeporting/qgis_fixes/fix_getcwdu.py
qgis2to3/codeporting/qgis_fixes/fix_has_key.py
qgis2to3/codeporting/qgis_fixes/fix_idioms.py
qgis2to3/codeporting/qgis_fixes/fix_input.py
qgis2to3/codeporting/qgis_fixes/fix_intern.py
qgis2to3/codeporting/qgis_fixes/fix_isinstance.py
qgis2to3/codeporting/qgis_fixes/fix_itertools.py
qgis2to3/codeporting/qgis_fixes/fix_itertools_imports.py
qgis2to3/codeporting/qgis_fixes/fix_long.py
qgis2to3/codeporting/qgis_fixes/fix_map.py
qgis2to3/codeporting/qgis_fixes/fix_metaclass.py
qgis2to3/codeporting/qgis_fixes/fix_methodattrs.py
qgis2to3/codeporting/qgis_fixes/fix_ne.py
qgis2to3/codeporting/qgis_fixes/fix_newstyle.py
qgis2to3/codeporting/qgis_fixes/fix_next_call.py
qgis2to3/codeporting/qgis_fixes/fix_nonzero.py
qgis2to3/codeporting/qgis_fixes/fix_numliterals.py
qgis2to3/codeporting/qgis_fixes/fix_object.py
qgis2to3/codeporting/qgis_fixes/fix_operator.py
qgis2to3/codeporting/qgis_fixes/fix_paren.py
