Metadata-Version: 1.2
Name: qgis2to3
Version: 0.4
Summary: Tools to help porting QGIS Plugins from api v2 to api v3
Home-page: https://github.com/opengisch/qgis2to3
Author: Marco Bernasocchi
Author-email: marco@opengis.ch
License: GPLv3
Download-URL: https://github.com/opengisch/qgis2to3/archive/0.4.tar.gz
Keywords: qgis,qgis2to3,porting
Platform: UNKNOWN
Classifier: Topic :: Database
Classifier: License :: OSI Approved :: GNU General Public License v3 or later (GPLv3+)
Classifier: Intended Audience :: Developers
Classifier: Intended Audience :: Information Technology
Classifier: Topic :: Software Development
Classifier: Topic :: Software Development :: Bug Tracking
Classifier: Development Status :: 4 - Beta
Requires-Python: ~=3.3
